README.rst
setup.py
tests/__init__.py
tests/test_countries.py
tests/test_utils.py
tests/test_vies.py
vat_validator/__init__.py
vat_validator/countries.py
vat_validator/utils.py
vat_validator/vies.py
vat_validator.egg-info/PKG-INFO
vat_validator.egg-info/SOURCES.txt
vat_validator.egg-info/dependency_links.txt
vat_validator.egg-info/requires.txt
vat_validator.egg-info/top_level.txt