Metadata-Version: 2.1
Name: vat-validator
Version: 0.1.1
Summary: VAT validation library
Home-page: https://github.com/ajcerejeira/vatval
Author: Afonso Silva
Author-email: ajcerejeira@gmail.com
License: MIT License
Platform: UNKNOWN
Classifier: Development Status :: 1 - Planning
Classifier: Intended Audience :: Developers
Classifier: Intended Audience :: Financial and Insurance Industry
Classifier: Programming Language :: Python :: 3
Classifier: License :: OSI Approved :: MIT License
Classifier: Operating System :: OS Independent
Classifier: Topic :: Office/Business :: Financial
Classifier: Topic :: Security :: Cryptography
Classifier: Topic :: Utilities
Classifier: Typing :: Typed
